somcaai.py
somcaai-0.0.1.dist-info/LICENSE
somcaai-0.0.1.dist-info/METADATA
somcaai-0.0.1.dist-info/WHEEL
somcaai-0.0.1.dist-info/top_level.txt
somcaai-0.0.1.dist-info/RECORD
