Metadata-Version: 2.1
Name: somcaai
Version: 0.0.1
Summary: somcaai common functions
Home-page: UNKNOWN
Author: Vitor Sousa
License: UNKNOWN
Platform: UNKNOWN
Classifier: Programming Language :: Python :: 3
Classifier: License :: OSI Approved :: MIT License
Classifier: Operating System :: OS Independent
Requires-Python: >=3.6
License-File: LICENSE
